tiltstack/__init__.py
tiltstack/_version.py
tiltstack/dask.py
tiltstack/io_utils.py
tiltstack/mdoc.py
tiltstack/stack_images.py
tiltstack/tiltstack.py
tiltstack/utils.py
tiltstack-0.0.1rc6.dist-info/LICENSE
tiltstack-0.0.1rc6.dist-info/METADATA
tiltstack-0.0.1rc6.dist-info/WHEEL
tiltstack-0.0.1rc6.dist-info/entry_points.txt
tiltstack-0.0.1rc6.dist-info/top_level.txt
tiltstack-0.0.1rc6.dist-info/RECORD
