Metadata-Version: 2.1
Name: tiltstack
Version: 0.0.1rc6
Summary: stack tilt images into tilt-series, keeping track of metadata
Home-page: https://github.com/alisterburt/tiltstack
Author: Alister Burt
Author-email: alisterburt@gmail.com
License: BSD-3-Clause
Project-URL: Source Code, https://github.com/alisterburt/tiltstack
Platform: UNKNOWN
Classifier: Development Status :: 2 - Pre-Alpha
Classifier: License :: OSI Approved :: BSD License
Classifier: Natural Language :: English
Classifier: Programming Language :: Python :: 3
Classifier: Programming Language :: Python :: 3 :: Only
Classifier: Programming Language :: Python :: 3.8
Classifier: Programming Language :: Python :: 3.9
Requires-Python: >=3.8
License-File: LICENSE
Requires-Dist: dask-ctl
Requires-Dist: dask-jobqueue
Requires-Dist: dask[distributed]
Requires-Dist: mrcfile
Requires-Dist: mdocfile
Requires-Dist: starfile
Requires-Dist: thefuzz[speedup]
Requires-Dist: typer
Provides-Extra: dev
Requires-Dist: black ; extra == 'dev'
Requires-Dist: flake8 ; extra == 'dev'
Requires-Dist: flake8-docstrings ; extra == 'dev'
Requires-Dist: ipython ; extra == 'dev'
Requires-Dist: isort ; extra == 'dev'
Requires-Dist: jedi (<0.18.0) ; extra == 'dev'
Requires-Dist: jupyter-book ; extra == 'dev'
Requires-Dist: mypy ; extra == 'dev'
Requires-Dist: pre-commit ; extra == 'dev'
Requires-Dist: pydocstyle ; extra == 'dev'
Requires-Dist: pytest ; extra == 'dev'
Provides-Extra: testing
Requires-Dist: pytest ; extra == 'testing'
